hexproof/__init__.py
hexproof/py.typed
hexproof/_cli/__init__.py
hexproof/_cli/test/__init__.py
hexproof/_cli/test/mtgjson.py
hexproof/_cli/test/scryfall.py
hexproof/_cli/test/vectors.py
hexproof/providers/__init__.py
hexproof/providers/cardmarket/__init__.py
hexproof/providers/cardmarket/constants/__init__.py
hexproof/providers/cardmarket/constants/urls.py
hexproof/providers/hexapi/__init__.py
hexproof/providers/hexapi/constants/__init__.py
hexproof/providers/hexapi/constants/urls.py
hexproof/providers/hexapi/schema/__init__.py
hexproof/providers/hexapi/schema/cards.py
hexproof/providers/hexapi/schema/meta.py
hexproof/providers/hexapi/schema/permissions.py
hexproof/providers/hexapi/schema/sets.py
hexproof/providers/hexapi/schema/symbols.py
hexproof/providers/mtgjson/__init__.py
hexproof/providers/mtgjson/fetch.py
hexproof/providers/mtgjson/constants/__init__.py
hexproof/providers/mtgjson/constants/urls.py
hexproof/providers/mtgjson/schema/__init__.py
hexproof/providers/mtgjson/schema/_core.py
hexproof/providers/mtgjson/schema/booster.py
hexproof/providers/mtgjson/schema/card.py
hexproof/providers/mtgjson/schema/card_type.py
hexproof/providers/mtgjson/schema/card_types.py
hexproof/providers/mtgjson/schema/deck.py
hexproof/providers/mtgjson/schema/deck_list.py
hexproof/providers/mtgjson/schema/deck_set.py
hexproof/providers/mtgjson/schema/foreign_data.py
hexproof/providers/mtgjson/schema/identifiers.py
hexproof/providers/mtgjson/schema/keywords.py
hexproof/providers/mtgjson/schema/leadership_skills.py
hexproof/providers/mtgjson/schema/legalities.py
hexproof/providers/mtgjson/schema/meta.py
hexproof/providers/mtgjson/schema/price.py
hexproof/providers/mtgjson/schema/purchase_urls.py
hexproof/providers/mtgjson/schema/related_cards.py
hexproof/providers/mtgjson/schema/rulings.py
hexproof/providers/mtgjson/schema/sealed_product.py
hexproof/providers/mtgjson/schema/set.py
hexproof/providers/mtgjson/schema/set_list.py
hexproof/providers/mtgjson/schema/source_products.py
hexproof-0.4.0.dist-info/METADATA
hexproof-0.4.0.dist-info/WHEEL
hexproof-0.4.0.dist-info/entry_points.txt
hexproof-0.4.0.dist-info/licenses/LICENSE.md
hexproof-0.4.0.dist-info/RECORD
